glglue/__init__.py
glglue/__main__.py
glglue/_version.py
glglue/frame_input.py
glglue/glfw.py
glglue/glut.py
glglue/gtk3.py
glglue/gtk4.py
glglue/pysdl2.py
glglue/pyside6.py
glglue/qgl4.py
glglue/qgl5.py
glglue/sdl.py
glglue/togl.py
glglue/util.py
glglue/wgl.py
glglue/win32con.py
glglue/windowconfig.py
glglue/wxglcanvas.py
glglue/glo/__init__.py
glglue/glo/drawable.py
glglue/glo/fbo.py
glglue/glo/shader.py
glglue/glo/texture.py
glglue/glo/vao.py
glglue/glo/vbo.py
glglue/glo/vertex_layout.py
glglue/scene/__init__.py
glglue/scene/camera.py
glglue/scene/mouse_camera.py
glglue/scene/mouse_event.py
glglue/scene/triangle.py
glglue-2.0.0.dist-info/LICENSE
glglue-2.0.0.dist-info/METADATA
glglue-2.0.0.dist-info/WHEEL
glglue-2.0.0.dist-info/top_level.txt
glglue-2.0.0.dist-info/RECORD
