Metadata-Version: 2.1
Name: glglue
Version: 2.0.0
Summary: The glue code which mediates between OpenGL and some GUI
Home-page: https://ousttrue.github.io/glglue/
Author: ousttrue
Author-email: ousttrue@gmail.com
Classifier: Programming Language :: Python :: 3.10
Classifier: License :: OSI Approved :: MIT License
Classifier: Topic :: Multimedia :: Graphics :: 3D Modeling
License-File: LICENSE
Requires-Dist: pyopengl
Provides-Extra: scene
Requires-Dist: PyGLM ; extra == 'scene'
